Metadata-Version: 2.1
Name: lineExtractor
Version: 0.0.1
Summary: A python CLI tool that allows you to extract certain lines from text files and transfer them to another file
Home-page: UNKNOWN
Author: kvanland
Author-email: kylevanlandingham9+lineExtractor@gmail.com
License: MIT
Platform: UNKNOWN
